HDF5DataModel/__init__.py
HDF5DataModel/version.py
HDF5DataModel/Model/__init__.py
HDF5DataModel/Model/attrsclasses.py
HDF5DataModel/Model/h5model.py
HDF5DataModel/Model/strict_parameter.py
HDF5DataModel/Model/subclasses.py
HDF5DataModel/View/__init__.py
HDF5DataModel/View/widget.py
HDF5DataModel/View/widget.ui
HDF5DataModel/utils/__init__.py
HDF5DataModel/utils/customparametertree.py
HDF5DataModel/utils/customtreeview.py
hdf5datamodel-0.3.2.dist-info/licenses/LICENSE
hdf5datamodel-0.3.2.dist-info/METADATA
hdf5datamodel-0.3.2.dist-info/WHEEL
hdf5datamodel-0.3.2.dist-info/top_level.txt
hdf5datamodel-0.3.2.dist-info/RECORD
