Metadata-Version: 2.4
Name: HDF5DataModel
Version: 0.3.2
Summary: A project for handling HDF5 data models
Author: Thibaud Devie, Maximilien Lehujeur
License:                    GNU LESSER GENERAL PUBLIC LICENSE
Requires-Python: >=3.8
License-File: LICENSE
Requires-Dist: toml
Requires-Dist: h5py>=3.6.0
Requires-Dist: numpy
Requires-Dist: PySide6>=6.2.0
Requires-Dist: pyqtgraph>=0.12.3
Requires-Dist: pyseg2>=1.4.6
Dynamic: license-file
